mlrl/__init__.py
mlrl/util/__init__.py
mlrl/util/arrays.py
mlrl/util/cli.py
mlrl/util/format.py
mlrl/util/options.py
mlrl/util/validation.py
mlrl/util/version.py
mlrl_util-0.15.1.dist-info/METADATA
mlrl_util-0.15.1.dist-info/WHEEL
mlrl_util-0.15.1.dist-info/top_level.txt
mlrl_util-0.15.1.dist-info/RECORD
