Metadata-Version: 2.4
Name: mlrl-util
Version: 0.15.1
Summary: Provides common utilities used by the mlrl-* packages.
Author-email: Michael Rapp <michael.rapp.ml@gmail.com>
License-Expression: MIT
Project-URL: homepage, https://github.com/mrapp-ke/MLRL-Boomer
Project-URL: source, https://github.com/mrapp-ke/MLRL-Boomer.git
Project-URL: download, https://github.com/mrapp-ke/MLRL-Boomer/releases
Project-URL: changelog, https://raw.githubusercontent.com/mrapp-ke/MLRL-Boomer/refs/heads/main/CHANGELOG.md
Project-URL: documentation, https://mlrl-boomer.readthedocs.io/en/latest
Project-URL: issues, https://github.com/mrapp-ke/MLRL-Boomer/issues
Keywords: utilities
Classifier: Development Status :: 5 - Production/Stable
Classifier: Intended Audience :: Science/Research
Classifier: Operating System :: OS Independent
Classifier: Programming Language :: Python :: 3
Classifier: Topic :: Software Development :: Libraries :: Python Modules
Requires-Python: >=3.12
Requires-Dist: numpy<2.4,>=2.3
Requires-Dist: scipy<1.17,>=1.16
